{
    "All": "23349",
    "Hokkaido": "23352",
    "Aomori": "23356",
    "Iwate": "23359",
    "Miyagi": "23362",
    "Akita": "23365",
    "Yamagata": "23368",
    "Fukushima": "23371",
    "Ibaraki": "23374",
    "Tochigi": "23377",
    "Gunma": "23380",
    "Saitama": "23383",
    "Chiba": "23387",
    "Tokyo": "23392",
    "Kanagawa": "23403",
    "Niigata": "23408",
    "Toyama": "23411",
    "Ishikawa": "23414",
    "Fukui": "23417",
    "Yamanashi": "23420",
    "Nagano": "23423",
    "Gifu": "23426",
    "Shizuoka": "23429",
    "Aichi": "23432",
    "Mie": "23436",
    "Shiga": "23439",
    "Kyoto": "23442",
    "Osaka": "23445",
    "Hyogo": "23450",
    "Nara": "23454",
    "Wakayama": "23457",
    "Tottori": "23460",
    "Shimane": "23463",
    "Okayama": "23466",
    "Hiroshima": "23469",
    "Yamaguchi": "23472",
    "Tokushima": "23475",
    "Kagawa": "23478",
    "Ehime": "23481",
    "Kochi": "23484",
    "Fukuoka": "23487",
    "Saga": "23491",
    "Nagasaki": "23494",
    "Kumamoto": "23497",
    "Oita": "23500",
    "Miyazaki": "23503",
    "Kagoshima": "23506",
    "Okinawa": "23509",
    "Other": "23512"
}